{
  "version": "7",
  "dialect": "mysql",
  "entries": [
    {
      "idx": 0,
      "version": "5",
      "when": 1772865337687,
      "tag": "0000_previous_ghost_rider",
      "breakpoints": true
    },
    {
      "idx": 1,
      "version": "5",
      "when": 1772865464573,
      "tag": "0001_dry_invaders",
      "breakpoints": true
    },
    {
      "idx": 2,
      "version": "5",
      "when": 1772866368356,
      "tag": "0002_panoramic_harrier",
      "breakpoints": true
    },
    {
      "idx": 3,
      "version": "5",
      "when": 1772871467156,
      "tag": "0003_marvelous_tempest",
      "breakpoints": true
    },
    {
      "idx": 4,
      "version": "5",
      "when": 1773020173620,
      "tag": "0004_optimal_magma",
      "breakpoints": true
    },
    {
      "idx": 5,
      "version": "5",
      "when": 1773026568775,
      "tag": "0005_mushy_squadron_sinister",
      "breakpoints": true
    },
    {
      "idx": 6,
      "version": "5",
      "when": 1773034860984,
      "tag": "0006_military_photon",
      "breakpoints": true
    },
    {
      "idx": 7,
      "version": "5",
      "when": 1773225940451,
      "tag": "0007_eminent_spirit",
      "breakpoints": true
    },
    {
      "idx": 8,
      "version": "5",
      "when": 1773229547036,
      "tag": "0008_sweet_talon",
      "breakpoints": true
    }
  ]
}